qlient/aiohttp/__init__.py
qlient/aiohttp/backends.py
qlient/aiohttp/clients.py
qlient/aiohttp/exceptions.py
qlient_aiohttp-0.1.0b2.dist-info/LICENSE
qlient_aiohttp-0.1.0b2.dist-info/WHEEL
qlient_aiohttp-0.1.0b2.dist-info/METADATA
qlient_aiohttp-0.1.0b2.dist-info/RECORD
