Metadata-Version: 2.1
Name: qlient-aiohttp
Version: 0.1.0b2
Summary: A blazingly fast and modern graphql client based on qlient-core and aiohttp
Author: Daniel Seifert
Author-email: info@danielseifert.ch
Maintainer: Daniel Seifert
Maintainer-email: info@danielseifert.ch
Requires-Python: >=3.7,<4.0
Classifier: Programming Language :: Python :: 3
Classifier: Programming Language :: Python :: 3.10
Classifier: Programming Language :: Python :: 3.7
Classifier: Programming Language :: Python :: 3.8
Classifier: Programming Language :: Python :: 3.9
Requires-Dist: aiohttp (>=3.8.1,<4.0.0)
Requires-Dist: qlient-core
